Instruments/DigitalScope.py
Instruments/KeySight_N670x.py
Instruments/KeySight_RP7954.py
Instruments/Keysight_34461.py
Instruments/Keysight_E362x.py
Instruments/__init__.py
Instruments/multimeter.py
IvmInstruments-0.2.9.dist-info/LICENSE
IvmInstruments-0.2.9.dist-info/METADATA
IvmInstruments-0.2.9.dist-info/WHEEL
IvmInstruments-0.2.9.dist-info/top_level.txt
IvmInstruments-0.2.9.dist-info/RECORD
