Metadata-Version: 2.1
Name: IvmInstruments
Version: 0.2.9
Summary: ['text/markdown', 'text/x-rst']
Home-page: https://github.com/HarishKumarSedu/Instruments
Author: HarishKumarSedu
Author-email: harishkumarsedu@gmail.com
Project-URL: Bug Tracker, https://github.com/HarishKumarSedu/Instruments/issues
License-File: LICENSE
